{
  "type": "Compass Connections",
  "version": {
    "$numberInt": "1"
  },
  "connections": [
    {
      "id": "054bf316-1ba9-45a5-9845-37ab0f890161",
      "lastUsed": {
        "$date": {
          "$numberLong": "1750409163772"
        }
      },
      "favorite": {
        "name": "MBD",
        "color": "color7"
      },
      "savedConnectionType": "recent",
      "connectionOptions": {
        "connectionString": "mongodb://localhost:27017/",
        "oidc": {
          "serializedState": "eyJvaWRjUGx1Z2luU3RhdGVWZXJzaW9uIjowLCJzdGF0ZSI6W119"
        }
      }
    }
  ]
}